{
  "schema_version": 1,
  "versions": [
    {
      "version": "1.0.0",
      "game_version": ">=1.0.0",
      "date": "2026-04-21",
      "changelog": "Initial public release. The atomic cities of southeastern Washington State - Kennewick, Pasco, and Richland, where the Columbia and Snake rivers meet.",
      "download": "https://github.com/ryandicicco/Subway-Builder-Maps/releases/download/v1.0.0-psc/PSC.zip",
      "sha256": "6f448d2dcf091a2f18acbc3406249109e6c844af1a9a6dd5be8614f24d364b1e"
    }
  ]
}
